GomezEngine
